odoo8_addon_hr_employee_legacy_id-8.0.1.0.0.99.dev10-py2.7-nspkg.pth
odoo8_addon_hr_employee_legacy_id-8.0.1.0.0.99.dev10.dist-info/DESCRIPTION.rst
odoo8_addon_hr_employee_legacy_id-8.0.1.0.0.99.dev10.dist-info/METADATA
odoo8_addon_hr_employee_legacy_id-8.0.1.0.0.99.dev10.dist-info/RECORD
odoo8_addon_hr_employee_legacy_id-8.0.1.0.0.99.dev10.dist-info/WHEEL
odoo8_addon_hr_employee_legacy_id-8.0.1.0.0.99.dev10.dist-info/metadata.json
odoo8_addon_hr_employee_legacy_id-8.0.1.0.0.99.dev10.dist-info/namespace_packages.txt
odoo8_addon_hr_employee_legacy_id-8.0.1.0.0.99.dev10.dist-info/top_level.txt
odoo_addons/hr_employee_legacy_id/README.rst
odoo_addons/hr_employee_legacy_id/__init__.py
odoo_addons/hr_employee_legacy_id/__openerp__.py
odoo_addons/hr_employee_legacy_id/i18n/ar.po
odoo_addons/hr_employee_legacy_id/i18n/de.po
odoo_addons/hr_employee_legacy_id/i18n/es.po
odoo_addons/hr_employee_legacy_id/i18n/fi.po
odoo_addons/hr_employee_legacy_id/i18n/fr.po
odoo_addons/hr_employee_legacy_id/i18n/hr_employee_legacy_id.pot
odoo_addons/hr_employee_legacy_id/i18n/it.po
odoo_addons/hr_employee_legacy_id/i18n/nl.po
odoo_addons/hr_employee_legacy_id/i18n/nl_NL.po
odoo_addons/hr_employee_legacy_id/i18n/pt_BR.po
odoo_addons/hr_employee_legacy_id/i18n/ro.po
odoo_addons/hr_employee_legacy_id/i18n/sl.po
odoo_addons/hr_employee_legacy_id/models/__init__.py
odoo_addons/hr_employee_legacy_id/models/hr.py
odoo_addons/hr_employee_legacy_id/static/description/icon.png
odoo_addons/hr_employee_legacy_id/views/hr_view.xml
